npiai_proto/api_pb2.py
npiai_proto/api_pb2.pyi
npiai_proto/api_pb2_grpc.py
npiai_proto-0.0.6.dist-info/METADATA
npiai_proto-0.0.6.dist-info/WHEEL
npiai_proto-0.0.6.dist-info/RECORD
